markdownify/__init__.py
markdownify/main.py
markdownify-0.14.0.dist-info/LICENSE
markdownify-0.14.0.dist-info/METADATA
markdownify-0.14.0.dist-info/WHEEL
markdownify-0.14.0.dist-info/entry_points.txt
markdownify-0.14.0.dist-info/top_level.txt
markdownify-0.14.0.dist-info/RECORD
