Metadata-Version: 2.1
Name: markdownify
Version: 0.14.0
Summary: Convert HTML to markdown.
Author-email: Matthew Tretter <m@tthewwithanm.com>
Project-URL: Homepage, http://github.com/matthewwithanm/python-markdownify
Project-URL: Download, http://github.com/matthewwithanm/python-markdownify/tarball/master
Classifier: Environment :: Web Environment
Classifier: Framework :: Django
Classifier: Intended Audience :: Developers
Classifier: License :: OSI Approved :: MIT License
Classifier: Operating System :: OS Independent
Classifier: Programming Language :: Python :: 2.5
Classifier: Programming Language :: Python :: 2.6
Classifier: Programming Language :: Python :: 2.7
Classifier: Programming Language :: Python :: 3.6
Classifier: Programming Language :: Python :: 3.7
Classifier: Programming Language :: Python :: 3.8
Classifier: Topic :: Utilities
License-File: LICENSE
Requires-Dist: beautifulsoup4<5,>=4.9
Requires-Dist: six<2,>=1.15
